pyside6_utils/__init__.py
pyside6_utils/constants.py
pyside6_utils/classes/__init__.py
pyside6_utils/classes/constraints.py
pyside6_utils/classes/serializable.py
pyside6_utils/examples/__init__.py
pyside6_utils/examples/example_dataclass.py
pyside6_utils/examples/run_qt_designer.py
pyside6_utils/examples/run_widgets_example_app.py
pyside6_utils/icons/__init__.py
pyside6_utils/icons/app_resources_rc.py
pyside6_utils/models/__init__.py
pyside6_utils/models/dataclass_model.py
pyside6_utils/models/dataclass_tree_item.py
pyside6_utils/models/extended_sort_filter_proxy_model.py
pyside6_utils/models/file_explorer_model.py
pyside6_utils/models/pandas_table_model.py
pyside6_utils/models/console_widget_models/__init__.py
pyside6_utils/models/console_widget_models/console_from_file_item.py
pyside6_utils/models/console_widget_models/console_model.py
pyside6_utils/registrars/__init__.py
pyside6_utils/registrars/register_collapsible_group_box.py
pyside6_utils/registrars/register_console_widget.py
pyside6_utils/registrars/register_extended_mdi_area.py
pyside6_utils/registrars/register_file_explorer_view.py
pyside6_utils/registrars/register_overlay_widget.py
pyside6_utils/registrars/register_pandas_table.py
pyside6_utils/registrars/register_range_selector.py
pyside6_utils/registrars/register_square_frame.py
pyside6_utils/registrars/register_widget_list.py
pyside6_utils/registrars/register_widget_switcher.py
pyside6_utils/ui/ConsoleWidget_ui.py
pyside6_utils/ui/FramelessMdiWindow_ui.py
pyside6_utils/ui/__init__.py
pyside6_utils/ui/allWidgets_ui.py
pyside6_utils/utility/__init__.py
pyside6_utils/utility/catch_show_exception_in_popup_decorator.py
pyside6_utils/utility/signal_blocker.py
pyside6_utils/utility/utility_functions.py
pyside6_utils/widgets/__init__.py
pyside6_utils/widgets/collapsible_group_box.py
pyside6_utils/widgets/console_widget.py
pyside6_utils/widgets/dataclass_tree_view.py
pyside6_utils/widgets/extended_mdi_area.py
pyside6_utils/widgets/file_explorer_view.py
pyside6_utils-1.2.2.dist-info/LICENSE
pyside6_utils-1.2.2.dist-info/METADATA
pyside6_utils-1.2.2.dist-info/WHEEL
pyside6_utils-1.2.2.dist-info/top_level.txt
pyside6_utils-1.2.2.dist-info/RECORD
