Metadata-Version: 2.1
Name: pyside6-utils
Version: 1.2.2
Summary: A collection of useful widgets and utilities for PySide6 compatible with pyside6-designer.
Home-page: https://github.com/Woutah/pyside6-utils
Author: Wouter Stokman
License: LPGPLv2
License-File: LICENSE
Requires-Dist: pandas >=1.5.2
Requires-Dist: numpy >=1.0.0
Requires-Dist: PySide6 >=6.0.0
Requires-Dist: pathos >=0.3.0
Requires-Dist: setuptools >=65.0.0
Requires-Dist: winshell >=0.6 ; platform_system == "Windows"
